monstr_terminal/__about__.py
monstr_terminal/__init__.py
monstr_terminal/alias.py
monstr_terminal/mirror.py
monstr_terminal/post.py
monstr_terminal/profile_search.py
monstr_terminal/run_relay.py
monstr_terminal/signer.py
monstr_terminal/util.py
monstr_terminal/view.py
monstr_terminal/view_consumer.py
monstr_terminal/app/__init__.py
monstr_terminal/app/post.py
monstr_terminal/cmd_line/__init__.py
monstr_terminal/cmd_line/message_app.py
monstr_terminal/cmd_line/post_loop_app.py
monstr_terminal/cmd_line/util.py
monstr_terminal-0.1.5.dist-info/METADATA
monstr_terminal-0.1.5.dist-info/WHEEL
monstr_terminal-0.1.5.dist-info/licenses/LICENSE
monstr_terminal-0.1.5.dist-info/RECORD
