Metadata-Version: 2.3
Name: monstr-terminal
Version: 0.1.5
Summary: Monstr Terminal: command line tools for nostr
Project-URL: Documentation, https://github.com/monty888/monstr_terminal#readme
Project-URL: Issues, https://github.com/monty888/monstr_terminal/issues
Project-URL: Source, https://github.com/monty888/monstr_terminal
Author-email: monty <monty@monty888.com>
License-Expression: MIT
License-File: LICENSE
Classifier: Development Status :: 4 - Beta
Classifier: Programming Language :: Python :: 3.10
Classifier: Programming Language :: Python :: 3.11
Classifier: Programming Language :: Python :: 3.12
Classifier: Programming Language :: Python :: Implementation :: CPython
Classifier: Programming Language :: Python :: Implementation :: PyPy
Requires-Python: >=3.10
Requires-Dist: monstr>=0.1.9
Requires-Dist: prompt-toolkit>=3.0.38
Requires-Dist: toml>=0.10.2
